the_artisans_shared/__init__.py
the_artisans_shared/errors/__init__.py
the_artisans_shared/errors/bad_request_error.py
the_artisans_shared/errors/custom_error.py
the_artisans_shared/errors/not_authorized_error.py
the_artisans_shared/errors/not_found_error.py
the_artisans_shared/errors/request_validation_error.py
the_artisans_shared/events/__init__.py
the_artisans_shared/events/base_listener.py
the_artisans_shared/events/base_publisher.py
the_artisans_shared/events/subjects.py
the_artisans_shared/middleware/__init__.py
the_artisans_shared/middleware/cookie_session.py
the_artisans_shared/middleware/current_user.py
the_artisans_shared/middleware/exception_handler.py
the_artisans_shared/middleware/require_auth.py
the_artisans_shared/middleware/validate_request.py
the_artisans_shared/types/__init__.py
the_artisans_shared/types/subscription.py
the_artisans_shared/types/user_roles.py
theartisans_shared_python-0.1.1.data/scripts/bad_request_error.py
theartisans_shared_python-0.1.1.data/scripts/base_listener.py
theartisans_shared_python-0.1.1.data/scripts/base_publisher.py
theartisans_shared_python-0.1.1.data/scripts/cookie_session.py
theartisans_shared_python-0.1.1.data/scripts/current_user.py
theartisans_shared_python-0.1.1.data/scripts/custom_error.py
theartisans_shared_python-0.1.1.data/scripts/exception_handler.py
theartisans_shared_python-0.1.1.data/scripts/not_authorized_error.py
theartisans_shared_python-0.1.1.data/scripts/not_found_error.py
theartisans_shared_python-0.1.1.data/scripts/request_validation_error.py
theartisans_shared_python-0.1.1.data/scripts/require_auth.py
theartisans_shared_python-0.1.1.data/scripts/subjects.py
theartisans_shared_python-0.1.1.data/scripts/subscription.py
theartisans_shared_python-0.1.1.data/scripts/user_roles.py
theartisans_shared_python-0.1.1.data/scripts/validate_request.py
theartisans_shared_python-0.1.1.dist-info/LICENCE
theartisans_shared_python-0.1.1.dist-info/METADATA
theartisans_shared_python-0.1.1.dist-info/WHEEL
theartisans_shared_python-0.1.1.dist-info/top_level.txt
theartisans_shared_python-0.1.1.dist-info/RECORD
